[{"dataverse_id": 716, "title": "Faculty of Psychology and Neuroscience", "dataverse_alias": "FacultyofPsychologyandNeuroscience", "type": "dataverse", "children": [{"dataverse_id": 157, "title": "Clinical Psychological Science", "dataverse_alias": "CPS", "type": "dataverse", "children": [{"dataset_id": 435, "pid": "doi:10.34894/CTDUVD", "type": "dataset", "children": []}, {"dataset_id": 436, "pid": "doi:10.34894/9EXOFE", "type": "dataset", "children": []}, {"dataset_id": 437, "pid": "doi:10.34894/FFCOKX", "type": "dataset", "children": []}, {"dataset_id": 438, "pid": "doi:10.34894/AVBSW9", "type": "dataset", "children": []}, {"dataset_id": 439, "pid": "doi:10.34894/QA0WSV", "type": "dataset", "children": []}, {"dataset_id": 440, "pid": "doi:10.34894/XJVTDE", "type": "dataset", "children": []}, {"dataset_id": 441, "pid": "doi:10.34894/VPX8M5", "type": "dataset", "children": []}, {"dataset_id": 442, "pid": "doi:10.34894/CXFUN2", "type": "dataset", "children": []}, {"dataset_id": 4128, "pid": "doi:10.34894/VLKCB9", "type": "dataset", "children": []}, {"dataset_id": 6523, "pid": "doi:10.34894/6JVGKV", "type": "dataset", "children": []}, {"dataset_id": 7074, "pid": "doi:10.34894/TISAGC", "type": "dataset", "children": []}, {"dataset_id": 8020, "pid": "doi:10.34894/5TRZSH", "type": "dataset", "children": []}, {"dataset_id": 8576, "pid": "doi:10.34894/YF3DI3", "type": "dataset", "children": []}, {"dataset_id": 8587, "pid": "doi:10.34894/B8W1JF", "type": "dataset", "children": []}, {"dataset_id": 9063, "pid": "doi:10.34894/FMSGLP", "type": "dataset", "children": []}, {"dataset_id": 9386, "pid": "doi:10.34894/ECOV4Q", "type": "dataset", "children": []}, {"dataset_id": 9392, "pid": "doi:10.34894/J3FUQM", "type": "dataset", "children": []}, {"dataset_id": 9398, "pid": "doi:10.34894/EW9JXQ", "type": "dataset", "children": []}, {"dataset_id": 9622, "pid": "doi:10.34894/PPYDCD", "type": "dataset", "children": []}, {"dataset_id": 11584, "pid": "doi:10.34894/37NY42", "type": "dataset", "children": []}, {"dataset_id": 11645, "pid": "doi:10.34894/CLJASV", "type": "dataset", "children": []}, {"dataset_id": 12041, "pid": "doi:10.34894/S98F15", "type": "dataset", "children": []}, {"dataset_id": 12051, "pid": "doi:10.34894/9YZ8DA", "type": "dataset", "children": []}, {"dataset_id": 12093, "pid": "doi:10.34894/JXFPEI", "type": "dataset", "children": []}, {"dataset_id": 12098, "pid": "doi:10.34894/F08TYS", "type": "dataset", "children": []}, {"dataset_id": 12099, "pid": "doi:10.34894/ZFCIIG", "type": "dataset", "children": []}, {"dataset_id": 12103, "pid": "doi:10.34894/N9UMFW", "type": "dataset", "children": []}, {"dataset_id": 12162, "pid": "doi:10.34894/3SPCPE", "type": "dataset", "children": []}, {"dataset_id": 12395, "pid": "doi:10.34894/IEBO9K", "type": "dataset", "children": []}, {"dataset_id": 12408, "pid": "doi:10.34894/CSWV6R", "type": "dataset", "children": []}, {"dataset_id": 13782, "pid": "doi:10.34894/J3HPR4", "type": "dataset", "children": []}, {"dataset_id": 14861, "pid": "doi:10.34894/QXU1DG", "type": "dataset", "children": []}, {"dataset_id": 15183, "pid": "doi:10.34894/YDXP6Z", "type": "dataset", "children": []}, {"dataset_id": 15279, "pid": "doi:10.34894/QXQPRQ", "type": "dataset", "children": []}, {"dataset_id": 15480, "pid": "doi:10.34894/LLNXJY", "type": "dataset", "children": []}, {"dataset_id": 15683, "pid": "doi:10.34894/40VFZE", "type": "dataset", "children": []}, {"dataset_id": 15745, "pid": "doi:10.34894/MCSWVI", "type": "dataset", "children": []}, {"dataset_id": 15939, "pid": "doi:10.34894/QSFGNC", "type": "dataset", "children": []}, {"dataset_id": 15954, "pid": "doi:10.34894/SDPIFR", "type": "dataset", "children": []}, {"dataset_id": 15978, "pid": "doi:10.34894/GFB1UN", "type": "dataset", "children": []}, {"dataset_id": 16388, "pid": "doi:10.34894/WW6WQB", "type": "dataset", "children": []}, {"dataset_id": 16999, "pid": "doi:10.34894/2VPOU7", "type": "dataset", "children": []}, {"dataset_id": 17398, "pid": "doi:10.34894/YMNBUA", "type": "dataset", "children": []}, {"dataset_id": 17653, "pid": "doi:10.34894/34FWGO", "type": "dataset", "children": []}, {"dataset_id": 17655, "pid": "doi:10.34894/NNGOUG", "type": "dataset", "children": []}, {"dataset_id": 19444, "pid": "doi:10.34894/XL3GBF", "type": "dataset", "children": []}, {"dataset_id": 21042, "pid": "doi:10.34894/GQKRUF", "type": "dataset", "children": []}, {"dataset_id": 21051, "pid": "doi:10.34894/0VERPQ", "type": "dataset", "children": []}, {"dataset_id": 21938, "pid": "doi:10.34894/IKCMDK", "type": "dataset", "children": []}, {"dataset_id": 21978, "pid": "doi:10.34894/L8XFPZ", "type": "dataset", "children": []}, {"dataset_id": 21980, "pid": "doi:10.34894/FPWRLZ", "type": "dataset", "children": []}, {"dataset_id": 25347, "pid": "doi:10.34894/K2WQT3", "type": "dataset", "children": []}, {"dataset_id": 25350, "pid": "doi:10.34894/GHPXC2", "type": "dataset", "children": []}, {"dataset_id": 25353, "pid": "doi:10.34894/AIL5AW", "type": "dataset", "children": []}, {"dataset_id": 25355, "pid": "doi:10.34894/QEO2ZF", "type": "dataset", "children": []}, {"dataset_id": 25365, "pid": "doi:10.34894/Q5D2HI", "type": "dataset", "children": []}, {"dataset_id": 25367, "pid": "doi:10.34894/SZHV9R", "type": "dataset", "children": []}, {"dataset_id": 26906, "pid": "doi:10.34894/YRLQZ0", "type": "dataset", "children": []}, {"dataset_id": 26939, "pid": "doi:10.34894/2BPVSB", "type": "dataset", "children": []}, {"dataset_id": 36545, "pid": "doi:10.34894/DKYQQY", "type": "dataset", "children": []}, {"dataset_id": 36553, "pid": "doi:10.34894/OMPSAU", "type": "dataset", "children": []}, {"dataset_id": 36564, "pid": "doi:10.34894/UQ275L", "type": "dataset", "children": []}, {"dataset_id": 37969, "pid": "doi:10.34894/7NSOR2", "type": "dataset", "children": []}, {"dataset_id": 38197, "pid": "doi:10.34894/DYNSCY", "type": "dataset", "children": []}, {"dataset_id": 39385, "pid": "doi:10.34894/IRP9YE", "type": "dataset", "children": []}, {"dataset_id": 40102, "pid": "doi:10.34894/LG2XPI", "type": "dataset", "children": []}, {"dataset_id": 47220, "pid": "doi:10.34894/2H1ZBP", "type": "dataset", "children": []}, {"dataset_id": 47586, "pid": "doi:10.34894/5JDANR", "type": "dataset", "children": []}, {"dataset_id": 49561, "pid": "doi:10.34894/HPSWNV", "type": "dataset", "children": []}, {"dataset_id": 94441, "pid": "doi:10.34894/IXGK7R", "type": "dataset", "children": []}, {"dataset_id": 94453, "pid": "doi:10.34894/D8VIVN", "type": "dataset", "children": []}, {"dataset_id": 94480, "pid": "doi:10.34894/0KSIPK", "type": "dataset", "children": []}, {"dataset_id": 94482, "pid": "doi:10.34894/JQGSEE", "type": "dataset", "children": []}, {"dataset_id": 94588, "pid": "doi:10.34894/UBMGBV", "type": "dataset", "children": []}, {"dataset_id": 95995, "pid": "doi:10.34894/2DLLOV", "type": "dataset", "children": []}, {"dataset_id": 138794, "pid": "doi:10.34894/WLEA4O", "type": "dataset", "children": []}, {"dataset_id": 141176, "pid": "doi:10.34894/95OYIS", "type": "dataset", "children": []}, {"dataset_id": 193857, "pid": "doi:10.34894/J5EKAR", "type": "dataset", "children": []}, {"dataset_id": 195132, "pid": "doi:10.34894/8QNWZC", "type": "dataset", "children": []}, {"dataset_id": 195150, "pid": "doi:10.34894/SQCSDD", "type": "dataset", "children": []}, {"dataset_id": 195162, "pid": "doi:10.34894/Y2TAJ9", "type": "dataset", "children": []}, {"dataset_id": 199361, "pid": "doi:10.34894/4YRK6U", "type": "dataset", "children": []}, {"dataset_id": 223648, "pid": "doi:10.34894/2UZLNW", "type": "dataset", "children": []}, {"dataset_id": 269065, "pid": "doi:10.34894/O2QNME", "type": "dataset", "children": []}, {"dataset_id": 269070, "pid": "doi:10.34894/P2IJ8C", "type": "dataset", "children": []}, {"dataset_id": 297888, "pid": "doi:10.34894/IMRDQK", "type": "dataset", "children": []}, {"dataset_id": 299396, "pid": "doi:10.34894/NDIZI1", "type": "dataset", "children": []}, {"dataset_id": 303237, "pid": "doi:10.34894/WXMXU4", "type": "dataset", "children": []}, {"dataset_id": 303517, "pid": "doi:10.34894/UYSS04", "type": "dataset", "children": []}, {"dataset_id": 310292, "pid": "doi:10.34894/HJDM5V", "type": "dataset", "children": []}, {"dataset_id": 310294, "pid": "doi:10.34894/JF3Y5T", "type": "dataset", "children": []}, {"dataset_id": 314346, "pid": "doi:10.34894/AY87EJ", "type": "dataset", "children": []}, {"dataset_id": 314389, "pid": "doi:10.34894/R4BUBC", "type": "dataset", "children": []}, {"dataset_id": 314391, "pid": "doi:10.34894/YEIRRD", "type": "dataset", "children": []}, {"dataset_id": 318357, "pid": "doi:10.34894/4GK3IP", "type": "dataset", "children": []}, {"dataset_id": 326330, "pid": "doi:10.34894/ILFUQC", "type": "dataset", "children": []}, {"dataset_id": 353241, "pid": "doi:10.34894/II908V", "type": "dataset", "children": []}, {"dataset_id": 354235, "pid": "doi:10.34894/VDK1L5", "type": "dataset", "children": []}, {"dataset_id": 356815, "pid": "doi:10.34894/XYUBY8", "type": "dataset", "children": []}]}, {"dataverse_id": 158, "title": "Work & Social Psychology", "dataverse_alias": "WSP", "type": "dataverse", "children": [{"dataset_id": 455, "pid": "doi:10.34894/6BK2FT", "type": "dataset", "children": []}, {"dataset_id": 10397, "pid": "doi:10.34894/NQSXIY", "type": "dataset", "children": []}, {"dataset_id": 10674, "pid": "doi:10.34894/I7XHJG", "type": "dataset", "children": []}, {"dataset_id": 12137, "pid": "doi:10.34894/QGMYOM", "type": "dataset", "children": []}, {"dataset_id": 12248, "pid": "doi:10.34894/OHIRGP", "type": "dataset", "children": []}, {"dataset_id": 13151, "pid": "doi:10.34894/4VYBCH", "type": "dataset", "children": []}, {"dataset_id": 14411, "pid": "doi:10.34894/OVJLRK", "type": "dataset", "children": []}, {"dataset_id": 14534, "pid": "doi:10.34894/JDZJUL", "type": "dataset", "children": []}, {"dataset_id": 14863, "pid": "doi:10.34894/RFI0L9", "type": "dataset", "children": []}, {"dataset_id": 14872, "pid": "doi:10.34894/JISC6X", "type": "dataset", "children": []}, {"dataset_id": 15528, "pid": "doi:10.34894/RS039E", "type": "dataset", "children": []}, {"dataset_id": 27954, "pid": "doi:10.34894/YMLHMD", "type": "dataset", "children": []}, {"dataset_id": 31996, "pid": "doi:10.34894/D4FCRX", "type": "dataset", "children": []}, {"dataset_id": 34347, "pid": "doi:10.34894/IQ5SJH", "type": "dataset", "children": []}, {"dataset_id": 34455, "pid": "doi:10.34894/WEF1B9", "type": "dataset", "children": []}, {"dataset_id": 34760, "pid": "doi:10.34894/CMOKVS", "type": "dataset", "children": []}, {"dataset_id": 34811, "pid": "doi:10.34894/EU24S5", "type": "dataset", "children": []}, {"dataset_id": 39722, "pid": "doi:10.34894/IP1D7X", "type": "dataset", "children": []}, {"dataset_id": 47254, "pid": "doi:10.34894/Y3JA6C", "type": "dataset", "children": []}, {"dataset_id": 49025, "pid": "doi:10.34894/SNUAYN", "type": "dataset", "children": []}, {"dataset_id": 94248, "pid": "doi:10.34894/5IBFVG", "type": "dataset", "children": []}, {"dataset_id": 94254, "pid": "doi:10.34894/IANZME", "type": "dataset", "children": []}, {"dataset_id": 94455, "pid": "doi:10.34894/KGSQJL", "type": "dataset", "children": []}, {"dataset_id": 94539, "pid": "doi:10.34894/2CYFIO", "type": "dataset", "children": []}, {"dataset_id": 137494, "pid": "doi:10.34894/TN757C", "type": "dataset", "children": []}, {"dataset_id": 137499, "pid": "doi:10.34894/RQAD2H", "type": "dataset", "children": []}, {"dataset_id": 137867, "pid": "doi:10.34894/I44QZT", "type": "dataset", "children": []}, {"dataset_id": 192667, "pid": "doi:10.34894/WSKBFB", "type": "dataset", "children": []}, {"dataset_id": 192683, "pid": "doi:10.34894/3TCREN", "type": "dataset", "children": []}, {"dataset_id": 192764, "pid": "doi:10.34894/KT1C2O", "type": "dataset", "children": []}, {"dataset_id": 192779, "pid": "doi:10.34894/NN0JU6", "type": "dataset", "children": []}, {"dataset_id": 203639, "pid": "doi:10.34894/Z6FUNK", "type": "dataset", "children": []}, {"dataset_id": 228194, "pid": "doi:10.34894/2X0ABJ", "type": "dataset", "children": []}, {"dataset_id": 304082, "pid": "doi:10.34894/0DQ5TU", "type": "dataset", "children": []}, {"dataset_id": 353927, "pid": "doi:10.34894/JECS9U", "type": "dataset", "children": []}, {"dataset_id": 356881, "pid": "doi:10.34894/2ZGL85", "type": "dataset", "children": []}, {"dataset_id": 356912, "pid": "doi:10.34894/DXGHOI", "type": "dataset", "children": []}]}, {"dataverse_id": 159, "title": "Neuropsychology & Psychopharmacology", "dataverse_alias": "NP", "type": "dataverse", "children": [{"dataset_id": 427, "pid": "doi:10.34894/AVWNL1", "type": "dataset", "children": []}, {"dataset_id": 428, "pid": "doi:10.34894/VLN5PZ", "type": "dataset", "children": []}, {"dataset_id": 429, "pid": "doi:10.34894/17AUY3", "type": "dataset", "children": []}, {"dataset_id": 8573, "pid": "doi:10.34894/FDSLVP", "type": "dataset", "children": []}, {"dataset_id": 8589, "pid": "doi:10.34894/0DUZZI", "type": "dataset", "children": []}, {"dataset_id": 13781, "pid": "doi:10.34894/M42K5J", "type": "dataset", "children": []}, {"dataset_id": 15533, "pid": "doi:10.34894/3IHOR8", "type": "dataset", "children": []}, {"dataset_id": 15650, "pid": "doi:10.34894/IHO1FR", "type": "dataset", "children": []}, {"dataset_id": 21010, "pid": "doi:10.34894/ONLPHT", "type": "dataset", "children": []}, {"dataset_id": 21013, "pid": "doi:10.34894/WKVS64", "type": "dataset", "children": []}, {"dataset_id": 26936, "pid": "doi:10.34894/JQAEIR", "type": "dataset", "children": []}, {"dataset_id": 94449, "pid": "doi:10.34894/8UGJ0A", "type": "dataset", "children": []}, {"dataset_id": 94451, "pid": "doi:10.34894/AYUYQ1", "type": "dataset", "children": []}, {"dataset_id": 94486, "pid": "doi:10.34894/U7L4H4", "type": "dataset", "children": []}, {"dataset_id": 192761, "pid": "doi:10.34894/OZOYUA", "type": "dataset", "children": []}, {"dataset_id": 217793, "pid": "doi:10.34894/FJL5JD", "type": "dataset", "children": []}, {"dataset_id": 217794, "pid": "doi:10.34894/TWMP7M", "type": "dataset", "children": []}, {"dataset_id": 218134, "pid": "doi:10.34894/6XIHGK", "type": "dataset", "children": []}, {"dataset_id": 220248, "pid": "doi:10.34894/1PHIGF", "type": "dataset", "children": []}, {"dataset_id": 220295, "pid": "doi:10.34894/LTS4HZ", "type": "dataset", "children": []}, {"dataset_id": 220464, "pid": "doi:10.34894/MRJQZY", "type": "dataset", "children": []}, {"dataset_id": 221374, "pid": "doi:10.34894/FA2XYR", "type": "dataset", "children": []}, {"dataset_id": 236133, "pid": "doi:10.34894/2HYLT1", "type": "dataset", "children": []}, {"dataset_id": 269154, "pid": "doi:10.34894/ZPBCEO", "type": "dataset", "children": []}, {"dataset_id": 309866, "pid": "doi:10.34894/JR1T5Z", "type": "dataset", "children": []}, {"dataset_id": 314401, "pid": "doi:10.34894/U1YTW8", "type": "dataset", "children": []}, {"dataset_id": 320945, "pid": "doi:10.34894/PT7SIX", "type": "dataset", "children": []}, {"dataset_id": 320949, "pid": "doi:10.34894/NSSDCU", "type": "dataset", "children": []}]}, {"dataverse_id": 195, "title": "Cognitive Neuroscience", "dataverse_alias": "CN", "type": "dataverse", "children": [{"dataset_id": 612, "pid": "doi:10.34894/HXT0AT", "type": "dataset", "children": []}, {"dataset_id": 4098, "pid": "doi:10.34894/E1TZO1", "type": "dataset", "children": []}, {"dataset_id": 4127, "pid": "doi:10.34894/RD6MEZ", "type": "dataset", "children": []}, {"dataset_id": 9077, "pid": "doi:10.34894/JOWJF5", "type": "dataset", "children": []}, {"dataset_id": 11587, "pid": "doi:10.34894/UW5RA3", "type": "dataset", "children": []}, {"dataset_id": 11596, "pid": "doi:10.34894/AAAMTA", "type": "dataset", "children": []}, {"dataset_id": 11606, "pid": "doi:10.34894/HRKYX0", "type": "dataset", "children": []}, {"dataset_id": 11883, "pid": "doi:10.34894/VIQGGZ", "type": "dataset", "children": []}, {"dataset_id": 14508, "pid": "doi:10.34894/PQE3YB", "type": "dataset", "children": []}, {"dataset_id": 15245, "pid": "doi:10.34894/YUXSZZ", "type": "dataset", "children": []}, {"dataset_id": 15727, "pid": "doi:10.34894/FQEJVD", "type": "dataset", "children": []}, {"dataset_id": 17105, "pid": "doi:10.34894/SJUEXW", "type": "dataset", "children": []}, {"dataset_id": 17131, "pid": "doi:10.34894/DF83FF", "type": "dataset", "children": []}, {"dataset_id": 17637, "pid": "doi:10.34894/8RZTGK", "type": "dataset", "children": []}, {"dataset_id": 18456, "pid": "doi:10.34894/I732AY", "type": "dataset", "children": []}, {"dataset_id": 22404, "pid": "doi:10.34894/GMKHAA", "type": "dataset", "children": []}, {"dataset_id": 26734, "pid": "doi:10.34894/6KR8LY", "type": "dataset", "children": []}, {"dataset_id": 27229, "pid": "doi:10.34894/LZXIRK", "type": "dataset", "children": []}, {"dataset_id": 27246, "pid": "doi:10.34894/AGMMJA", "type": "dataset", "children": []}, {"dataset_id": 27984, "pid": "doi:10.34894/ETPJTX", "type": "dataset", "children": []}, {"dataset_id": 27985, "pid": "doi:10.34894/P4YCJ0", "type": "dataset", "children": []}, {"dataset_id": 30405, "pid": "doi:10.34894/3EDUG0", "type": "dataset", "children": []}, {"dataset_id": 31130, "pid": "doi:10.34894/5YNXRI", "type": "dataset", "children": []}, {"dataset_id": 31211, "pid": "doi:10.34894/7VP5OA", "type": "dataset", "children": []}, {"dataset_id": 31454, "pid": "doi:10.34894/SP4AWN", "type": "dataset", "children": []}, {"dataset_id": 38198, "pid": "doi:10.34894/GALD5F", "type": "dataset", "children": []}, {"dataset_id": 40457, "pid": "doi:10.34894/ITWFZP", "type": "dataset", "children": []}, {"dataset_id": 46661, "pid": "doi:10.34894/QSZBS6", "type": "dataset", "children": []}, {"dataset_id": 47077, "pid": "doi:10.34894/2LVRIF", "type": "dataset", "children": []}, {"dataset_id": 47560, "pid": "doi:10.34894/5HVGCF", "type": "dataset", "children": []}, {"dataset_id": 49439, "pid": "doi:10.34894/4OEBD9", "type": "dataset", "children": []}, {"dataset_id": 49699, "pid": "doi:10.34894/OUVYI5", "type": "dataset", "children": []}, {"dataset_id": 86573, "pid": "doi:10.34894/D0EUPE", "type": "dataset", "children": []}, {"dataset_id": 86584, "pid": "doi:10.34894/NCQFIZ", "type": "dataset", "children": []}, {"dataset_id": 94693, "pid": "doi:10.34894/RDE8DU", "type": "dataset", "children": []}, {"dataset_id": 100088, "pid": "doi:10.34894/R3QWKH", "type": "dataset", "children": []}, {"dataset_id": 106684, "pid": "doi:10.34894/KW3YKN", "type": "dataset", "children": []}, {"dataset_id": 137454, "pid": "doi:10.34894/1AWTCT", "type": "dataset", "children": []}, {"dataset_id": 138799, "pid": "doi:10.34894/9ITCNN", "type": "dataset", "children": []}, {"dataset_id": 199340, "pid": "doi:10.34894/ZZOTIF", "type": "dataset", "children": []}, {"dataset_id": 228684, "pid": "doi:10.34894/VWEXJE", "type": "dataset", "children": []}, {"dataset_id": 236050, "pid": "doi:10.34894/3LYMZF", "type": "dataset", "children": []}, {"dataset_id": 269064, "pid": "doi:10.34894/AXZIWF", "type": "dataset", "children": []}, {"dataset_id": 296575, "pid": "doi:10.34894/DREHB9", "type": "dataset", "children": []}, {"dataset_id": 298280, "pid": "doi:10.34894/WCUTUL", "type": "dataset", "children": []}, {"dataset_id": 300200, "pid": "doi:10.34894/SRT8RU", "type": "dataset", "children": []}, {"dataset_id": 303894, "pid": "doi:10.34894/FXOQ2Q", "type": "dataset", "children": []}, {"dataset_id": 320751, "pid": "doi:10.34894/H890ZU", "type": "dataset", "children": []}, {"dataset_id": 327297, "pid": "doi:10.34894/TZA9S8", "type": "dataset", "children": []}]}, {"dataverse_id": 314315, "title": "Methodology & Statistics FPN", "dataverse_alias": "mandsfpn", "type": "dataverse", "children": [{"dataset_id": 314323, "pid": "doi:10.34894/VHAFZL", "type": "dataset", "children": []}, {"dataset_id": 322716, "pid": "doi:10.34894/PWQHEC", "type": "dataset", "children": []}]}]}, {"dataverse_id": 717, "title": "Faculty of Business and Economics", "dataverse_alias": "FacultyofBusinessandEconomics", "type": "dataverse", "children": [{"dataverse_id": 151, "title": "BEElab", "dataverse_alias": "beelab", "type": "dataverse", "children": [{"dataset_id": 432, "pid": "doi:10.34894/KZISGA", "type": "dataset", "children": []}, {"dataset_id": 1293, "pid": "doi:10.34894/DR5ZS6", "type": "dataset", "children": []}, {"dataset_id": 1294, "pid": "doi:10.34894/GQROEB", "type": "dataset", "children": []}, {"dataset_id": 1295, "pid": "doi:10.34894/QMEVPT", "type": "dataset", "children": []}]}, {"dataverse_id": 161, "title": "Education Research and Development (ERD)", "dataverse_alias": "EOE", "type": "dataverse", "children": [{"dataset_id": 309127, "pid": "doi:10.34894/UZOLBE", "type": "dataset", "children": []}]}, {"dataverse_id": 18196, "title": "Accounting and Information Management (AIM)", "dataverse_alias": "AIM", "type": "dataverse", "children": [{"dataset_id": 18204, "pid": "doi:10.34894/RY1MOO", "type": "dataset", "children": []}, {"dataset_id": 47223, "pid": "doi:10.34894/VMQ6IG", "type": "dataset", "children": []}, {"dataset_id": 47225, "pid": "doi:10.34894/QZTTU5", "type": "dataset", "children": []}]}, {"dataverse_id": 18239, "title": "Quantitative Economics", "dataverse_alias": "QE", "type": "dataverse", "children": [{"dataset_id": 18244, "pid": "doi:10.34894/JHVJQS", "type": "dataset", "children": []}, {"dataset_id": 25234, "pid": "doi:10.34894/L1UMWV", "type": "dataset", "children": []}, {"dataset_id": 47078, "pid": "doi:10.34894/LVXSKZ", "type": "dataset", "children": []}, {"dataset_id": 111443, "pid": "doi:10.34894/FWJ66W", "type": "dataset", "children": []}]}, {"dataverse_id": 21375, "title": "Research Centre for Education and the Labour Market (ROA)", "dataverse_alias": "ROA", "type": "dataverse", "children": [{"dataverse_id": 21376, "title": "Technequality", "dataverse_alias": "Technequality", "type": "dataverse", "children": [{"dataverse_id": 21378, "title": "The future of work in Europe (WP1)", "dataverse_alias": "FWE_WP1", "type": "dataverse", "children": [{"dataset_id": 21383, "pid": "doi:10.34894/FVTR7S", "type": "dataset", "children": []}]}, {"dataverse_id": 21379, "title": "Educating today for tomorrows labour market (WP3)", "dataverse_alias": "ETLM_WP3", "type": "dataverse", "children": [{"dataset_id": 21381, "pid": "doi:10.34894/MERDXJ", "type": "dataset", "children": []}]}, {"dataverse_id": 31044, "title": "Automation, taxation, and public finances (WP5)", "dataverse_alias": "ATP_WP5", "type": "dataverse", "children": [{"dataset_id": 31045, "pid": "doi:10.34894/RGZNFE", "type": "dataset", "children": []}, {"dataset_id": 94253, "pid": "doi:10.34894/D25FN9", "type": "dataset", "children": []}]}]}, {"dataset_id": 354593, "pid": "doi:10.34894/9KL75I", "type": "dataset", "children": []}]}, {"dataverse_id": 25643, "title": "Data Analytics and Digitalisation (DAD)", "dataverse_alias": "Data_Analytics_Digitalisation", "type": "dataverse", "children": []}, {"dataverse_id": 25644, "title": "Finance", "dataverse_alias": "Finance", "type": "dataverse", "children": []}, {"dataverse_id": 25645, "title": "Macro, International and Labor Economics (MILE)", "dataverse_alias": "MILE", "type": "dataverse", "children": [{"dataset_id": 480, "pid": "doi:10.34894/8GJDFY", "type": "dataset", "children": []}, {"dataset_id": 100091, "pid": "doi:10.34894/CQGMTU", "type": "dataset", "children": []}]}, {"dataverse_id": 25646, "title": "Marketing and Supply Chain Management (MSCM)", "dataverse_alias": "MSCM", "type": "dataverse", "children": []}, {"dataverse_id": 25647, "title": "Microeconomics and Public Economics (MPE)", "dataverse_alias": "MPE", "type": "dataverse", "children": [{"dataset_id": 100100, "pid": "doi:10.34894/FWUT2K", "type": "dataset", "children": []}, {"dataset_id": 100101, "pid": "doi:10.34894/M4ECBL", "type": "dataset", "children": []}, {"dataset_id": 137471, "pid": "doi:10.34894/XPK1NP", "type": "dataset", "children": []}, {"dataset_id": 192641, "pid": "doi:10.34894/GOKFX1", "type": "dataset", "children": []}, {"dataset_id": 356893, "pid": "doi:10.34894/QYCPAM", "type": "dataset", "children": []}]}, {"dataverse_id": 25648, "title": "Organisation, Strategy and Entrepreneurship (OSE)", "dataverse_alias": "OSE", "type": "dataverse", "children": []}, {"dataverse_id": 25649, "title": "Maastricht Graduate School of Governance (MGSoG)", "dataverse_alias": "MGSoG", "type": "dataverse", "children": [{"dataset_id": 38192, "pid": "doi:10.34894/XSS05Q", "type": "dataset", "children": []}]}, {"dataverse_id": 25650, "title": "Maastricht Sustainability Institute (MSI)", "dataverse_alias": "MSI", "type": "dataverse", "children": []}]}, {"dataverse_id": 718, "title": "Faculty of Health, Medicine and Life Sciences", "dataverse_alias": "FacultyofHealthMedicine", "type": "dataverse", "children": [{"dataverse_id": 170, "title": "Limburg Twin Study", "dataverse_alias": "LTS", "type": "dataverse", "children": [{"dataset_id": 273, "pid": "doi:10.34894/BYSUAU", "type": "dataset", "children": []}]}, {"dataverse_id": 174, "title": "EFPTS", "dataverse_alias": "EFPTS", "type": "dataverse", "children": []}, {"dataverse_id": 212, "title": "BLADDER", "dataverse_alias": "BLADDER", "type": "dataverse", "children": []}, {"dataverse_id": 213, "title": "BCPP", "dataverse_alias": "BCPP", "type": "dataverse", "children": [{"dataset_id": 1246, "pid": "doi:10.34894/Q16KHD", "type": "dataset", "children": []}]}, {"dataverse_id": 221, "title": "Leef!", "dataverse_alias": "Leef", "type": "dataverse", "children": [{"dataset_id": 1290, "pid": "doi:10.34894/MHT6HW", "type": "dataset", "children": []}, {"dataset_id": 6372, "pid": "doi:10.34894/9DFOH7", "type": "dataset", "children": []}]}, {"dataverse_id": 222, "title": "Sound Science", "dataverse_alias": "SoundScience", "type": "dataverse", "children": [{"dataset_id": 651, "pid": "doi:10.34894/0TNI44", "type": "dataset", "children": []}, {"dataset_id": 652, "pid": "doi:10.34894/ECZHZQ", "type": "dataset", "children": []}, {"dataset_id": 653, "pid": "doi:10.34894/WNBXK3", "type": "dataset", "children": []}, {"dataset_id": 654, "pid": "doi:10.34894/H8CDZ2", "type": "dataset", "children": []}, {"dataset_id": 7474, "pid": "doi:10.34894/G0X6CS", "type": "dataset", "children": []}, {"dataset_id": 8499, "pid": "doi:10.34894/DQVJFN", "type": "dataset", "children": []}, {"dataset_id": 10945, "pid": "doi:10.34894/5RIYGP", "type": "dataset", "children": []}, {"dataset_id": 11492, "pid": "doi:10.34894/8NTFCX", "type": "dataset", "children": []}, {"dataset_id": 11732, "pid": "doi:10.34894/NMSJ2L", "type": "dataset", "children": []}, {"dataset_id": 11760, "pid": "doi:10.34894/3JT7XY", "type": "dataset", "children": []}, {"dataset_id": 13212, "pid": "doi:10.34894/3Z0RGS", "type": "dataset", "children": []}, {"dataset_id": 94268, "pid": "doi:10.34894/6DCACQ", "type": "dataset", "children": []}]}, {"dataverse_id": 226, "title": "MEFAB", "dataverse_alias": "MEFAB", "type": "dataverse", "children": []}, {"dataverse_id": 228, "title": "Tictac", "dataverse_alias": "tictac", "type": "dataverse", "children": [{"dataset_id": 491, "pid": "doi:10.34894/GSTE8K", "type": "dataset", "children": []}]}, {"dataverse_id": 715, "title": "School of Health Professions Education (SHE) ", "dataverse_alias": "SchoolofHealth", "type": "dataverse", "children": [{"dataverse_id": 93, "title": "Ellen Kok", "dataverse_alias": "EKok", "type": "dataverse", "children": [{"dataverse_id": 8265, "title": "Phillip Shek WESP data", "dataverse_alias": "Shekwespdata", "type": "dataverse", "children": [{"dataset_id": 8266, "pid": "doi:10.34894/JRSIKP", "type": "dataset", "children": []}, {"dataset_id": 8362, "pid": "doi:10.34894/79HTKE", "type": "dataset", "children": []}]}, {"dataverse_id": 39355, "title": "Ellen Kok - Holistic processing ", "dataverse_alias": "ellenkok-holisticprocessing", "type": "dataverse", "children": [{"dataset_id": 39356, "pid": "doi:10.34894/O0CKVP", "type": "dataset", "children": []}]}, {"dataset_id": 431, "pid": "doi:10.34894/XZZLS4", "type": "dataset", "children": []}, {"dataset_id": 1281, "pid": "doi:10.34894/DQLV5M", "type": "dataset", "children": []}, {"dataset_id": 1282, "pid": "doi:10.34894/GLPBZU", "type": "dataset", "children": []}, {"dataset_id": 1283, "pid": "doi:10.34894/M0WFTF", "type": "dataset", "children": []}, {"dataset_id": 1284, "pid": "doi:10.34894/TSUVG3", "type": "dataset", "children": []}, {"dataset_id": 1285, "pid": "doi:10.34894/WHWTGY", "type": "dataset", "children": []}, {"dataset_id": 4166, "pid": "doi:10.34894/ETYS8D", "type": "dataset", "children": []}]}, {"dataverse_id": 125, "title": "Shedata - Katerina Bohle Carbonell", "dataverse_alias": "katerina", "type": "dataverse", "children": [{"dataset_id": 460, "pid": "doi:10.34894/TOABJD", "type": "dataset", "children": []}, {"dataset_id": 461, "pid": "doi:10.34894/VZWEIC", "type": "dataset", "children": []}, {"dataset_id": 1277, "pid": "doi:10.34894/PWMMDF", "type": "dataset", "children": []}, {"dataset_id": 1278, "pid": "doi:10.34894/SREX7T", "type": "dataset", "children": []}, {"dataset_id": 1279, "pid": "doi:10.34894/BAUOEU", "type": "dataset", "children": []}]}, {"dataverse_id": 131, "title": "MHPE (quantitative assignments)", "dataverse_alias": "MHPE", "type": "dataverse", "children": []}, {"dataverse_id": 152, "title": "Shedata - Alina Smirnova", "dataverse_alias": "asmirnova", "type": "dataverse", "children": [{"dataset_id": 1262, "pid": "doi:10.34894/6WP1AM", "type": "dataset", "children": []}, {"dataset_id": 1263, "pid": "doi:10.34894/PS5ZX0", "type": "dataset", "children": []}]}, {"dataverse_id": 175, "title": "Shedata - Koos van Geel", "dataverse_alias": "KvG", "type": "dataverse", "children": [{"dataset_id": 1291, "pid": "doi:10.34894/OCH3DJ", "type": "dataset", "children": []}, {"dataset_id": 1292, "pid": "doi:10.34894/EMUZXT", "type": "dataset", "children": []}]}, {"dataverse_id": 184, "title": "Shedata - Lorette Stammen", "dataverse_alias": "LAS", "type": "dataverse", "children": [{"dataset_id": 1308, "pid": "doi:10.34894/QYV6GP", "type": "dataset", "children": []}, {"dataset_id": 1309, "pid": "doi:10.34894/PYSX5N", "type": "dataset", "children": []}]}, {"dataverse_id": 232, "title": "Shedata - Guy Bendemacher", "dataverse_alias": "QualityCulture", "type": "dataverse", "children": [{"dataset_id": 613, "pid": "doi:10.34894/V6OILP", "type": "dataset", "children": []}, {"dataset_id": 9566, "pid": "doi:10.34894/JJE0CA", "type": "dataset", "children": []}]}, {"dataverse_id": 252, "title": "Shedata - Nguyen Van Anh", "dataverse_alias": "PreventiveMedicineVN", "type": "dataverse", "children": [{"dataset_id": 1269, "pid": "doi:10.34894/3PH7YO", "type": "dataset", "children": []}]}, {"dataverse_id": 7077, "title": "Affordance perception in simulated medical emergency care situations", "dataverse_alias": "Affordance_perception_medical_simulation", "type": "dataverse", "children": []}, {"dataverse_id": 10575, "title": "Shedata - Jorrick Beckers", "dataverse_alias": "perflect", "type": "dataverse", "children": [{"dataset_id": 485, "pid": "doi:10.34894/BXIPGX", "type": "dataset", "children": []}, {"dataset_id": 486, "pid": "doi:10.34894/ESO8TS", "type": "dataset", "children": []}, {"dataset_id": 487, "pid": "doi:10.34894/MMSQUC", "type": "dataset", "children": []}, {"dataset_id": 488, "pid": "doi:10.34894/IGBXRA", "type": "dataset", "children": []}, {"dataset_id": 489, "pid": "doi:10.34894/7OSMJS", "type": "dataset", "children": []}]}, {"dataverse_id": 11974, "title": "Shedata - Hesham Marei", "dataverse_alias": "HeshamMarei", "type": "dataverse", "children": [{"dataset_id": 11975, "pid": "doi:10.34894/P93DGF", "type": "dataset", "children": []}]}, {"dataverse_id": 15369, "title": "Shedata - Adam Szulewski", "dataverse_alias": "shedata_adam_szulewski", "type": "dataverse", "children": [{"dataset_id": 15370, "pid": "doi:10.34894/KROLR2", "type": "dataset", "children": []}, {"dataset_id": 15373, "pid": "doi:10.34894/PPT3WF", "type": "dataset", "children": []}, {"dataset_id": 15407, "pid": "doi:10.34894/EMK3ZA", "type": "dataset", "children": []}, {"dataset_id": 15410, "pid": "doi:10.34894/0ZCDLJ", "type": "dataset", "children": []}, {"dataset_id": 15413, "pid": "doi:10.34894/IAOAAQ", "type": "dataset", "children": []}, {"dataset_id": 15417, "pid": "doi:10.34894/ZZB9WK", "type": "dataset", "children": []}]}, {"dataverse_id": 15420, "title": "Shedata - Michaela Wagner-Menghin", "dataverse_alias": "shedata-michaela-wagner-menghin", "type": "dataverse", "children": [{"dataset_id": 15421, "pid": "doi:10.34894/VBIJZK", "type": "dataset", "children": []}, {"dataset_id": 15437, "pid": "doi:10.34894/RKG6MG", "type": "dataset", "children": []}, {"dataset_id": 15450, "pid": "doi:10.34894/8BAIJL", "type": "dataset", "children": []}]}, {"dataverse_id": 15487, "title": "Shedata - Tiuri van Rossum", "dataverse_alias": "shedata-tiuri-van-rossum", "type": "dataverse", "children": [{"dataset_id": 15488, "pid": "doi:10.34894/DCDMFU", "type": "dataset", "children": []}, {"dataset_id": 15504, "pid": "doi:10.34894/3LSWKE", "type": "dataset", "children": []}, {"dataset_id": 15514, "pid": "doi:10.34894/EVYRHA", "type": "dataset", "children": []}]}, {"dataverse_id": 18475, "title": "Shedata - Makoto Kikukawa", "dataverse_alias": "shedata-makoto-kikukawa", "type": "dataverse", "children": [{"dataset_id": 18476, "pid": "doi:10.34894/YXH7RH", "type": "dataset", "children": []}, {"dataset_id": 18480, "pid": "doi:10.34894/JANNGT", "type": "dataset", "children": []}, {"dataset_id": 18485, "pid": "doi:10.34894/5A9CTW", "type": "dataset", "children": []}, {"dataset_id": 18489, "pid": "doi:10.34894/QUVWE2", "type": "dataset", "children": []}]}, {"dataverse_id": 21083, "title": "Shedata - Meredith Guiliani", "dataverse_alias": "shedata-meredith-guiliani", "type": "dataverse", "children": [{"dataset_id": 21084, "pid": "doi:10.34894/5KQ6MY", "type": "dataset", "children": []}, {"dataset_id": 21087, "pid": "doi:10.34894/0FWFAF", "type": "dataset", "children": []}, {"dataset_id": 21090, "pid": "doi:10.34894/UESGG0", "type": "dataset", "children": []}, {"dataset_id": 21101, "pid": "doi:10.34894/X2IYBI", "type": "dataset", "children": []}, {"dataset_id": 21102, "pid": "doi:10.34894/1ZCLCV", "type": "dataset", "children": []}]}, {"dataverse_id": 94469, "title": "Shedata - Andrea Oudkerk Pool", "dataverse_alias": "shedata-andrea-oudkerk-pool", "type": "dataverse", "children": [{"dataset_id": 94470, "pid": "doi:10.34894/LLJ4HN", "type": "dataset", "children": []}, {"dataset_id": 94489, "pid": "doi:10.34894/CLKEYZ", "type": "dataset", "children": []}, {"dataset_id": 94493, "pid": "doi:10.34894/OFMZGF", "type": "dataset", "children": []}]}, {"dataverse_id": 95754, "title": "Shedata - Sanne Rovers", "dataverse_alias": "shedata-sanne-rovers", "type": "dataverse", "children": [{"dataset_id": 95755, "pid": "doi:10.34894/VWNYER", "type": "dataset", "children": []}, {"dataset_id": 95766, "pid": "doi:10.34894/YNC8XJ", "type": "dataset", "children": []}, {"dataset_id": 95772, "pid": "doi:10.34894/MIFFRT", "type": "dataset", "children": []}, {"dataset_id": 95786, "pid": "doi:10.34894/71HSDF", "type": "dataset", "children": []}]}, {"dataverse_id": 105489, "title": "Shedata - Jonathan Ilgen", "dataverse_alias": "shedata-jonathan-ilgen", "type": "dataverse", "children": [{"dataset_id": 105490, "pid": "doi:10.34894/2GXSFJ", "type": "dataset", "children": []}, {"dataset_id": 105497, "pid": "doi:10.34894/5LKZIA", "type": "dataset", "children": []}]}, {"dataverse_id": 108610, "title": "Shedata - Laury de Jonge", "dataverse_alias": "shedata-laury-de-jonge", "type": "dataverse", "children": [{"dataset_id": 108611, "pid": "doi:10.34894/BZ6TAP", "type": "dataset", "children": []}, {"dataset_id": 108614, "pid": "doi:10.34894/6BS42J", "type": "dataset", "children": []}, {"dataset_id": 108619, "pid": "doi:10.34894/T0XVR1", "type": "dataset", "children": []}, {"dataset_id": 108622, "pid": "doi:10.34894/MKLCNI", "type": "dataset", "children": []}]}, {"dataverse_id": 111461, "title": "Shedata - Marlies Schillings", "dataverse_alias": "shedata-marlies-schillings", "type": "dataverse", "children": [{"dataset_id": 111462, "pid": "doi:10.34894/YJAFQG", "type": "dataset", "children": []}, {"dataset_id": 111508, "pid": "doi:10.34894/F8HBCA", "type": "dataset", "children": []}, {"dataset_id": 111559, "pid": "doi:10.34894/P4LFPZ", "type": "dataset", "children": []}, {"dataset_id": 137453, "pid": "doi:10.34894/OAJPEF", "type": "dataset", "children": []}]}, {"dataverse_id": 317859, "title": "Shedata - Juli\u00ebt Beuken", "dataverse_alias": "shedata-juliet-beuken", "type": "dataverse", "children": [{"dataset_id": 317860, "pid": "doi:10.34894/CJ0VXD", "type": "dataset", "children": []}, {"dataset_id": 317861, "pid": "doi:10.34894/DIWI5H", "type": "dataset", "children": []}, {"dataset_id": 317862, "pid": "doi:10.34894/QSW2ZE", "type": "dataset", "children": []}, {"dataset_id": 317863, "pid": "doi:10.34894/IYEMO2", "type": "dataset", "children": []}]}, {"dataset_id": 13221, "pid": "doi:10.34894/KNZ6GL", "type": "dataset", "children": []}]}, {"dataverse_id": 5757, "title": "MHeNs ", "dataverse_alias": "MHeNs", "type": "dataverse", "children": [{"dataset_id": 6022, "pid": "doi:10.34894/YPYO3M", "type": "dataset", "children": []}, {"dataset_id": 8442, "pid": "doi:10.34894/JYOWJG", "type": "dataset", "children": []}, {"dataset_id": 10703, "pid": "doi:10.34894/MDABH5", "type": "dataset", "children": []}, {"dataset_id": 21057, "pid": "doi:10.34894/5HHK8H", "type": "dataset", "children": []}, {"dataset_id": 23444, "pid": "doi:10.34894/FUTGYT", "type": "dataset", "children": []}, {"dataset_id": 296250, "pid": "doi:10.34894/NDQC2O", "type": "dataset", "children": []}]}, {"dataverse_id": 6235, "title": "KOALA", "dataverse_alias": "KOALA", "type": "dataverse", "children": [{"dataset_id": 6236, "pid": "doi:10.34894/XXKTHT", "type": "dataset", "children": []}]}, {"dataverse_id": 9056, "title": "NUTRIM", "dataverse_alias": "nutrim", "type": "dataverse", "children": [{"dataverse_id": 9057, "title": "BiGCaT ", "dataverse_alias": "BiGCaT", "type": "dataverse", "children": [{"dataset_id": 490, "pid": "doi:10.34894/IJWU5L", "type": "dataset", "children": []}]}, {"dataset_id": 296865, "pid": "doi:10.34894/3TYPA4", "type": "dataset", "children": []}]}, {"dataverse_id": 12111, "title": "GROW", "dataverse_alias": "GROW", "type": "dataverse", "children": [{"dataset_id": 12112, "pid": "doi:10.34894/BIU9RK", "type": "dataset", "children": []}, {"dataset_id": 46766, "pid": "doi:10.34894/UKGYLR", "type": "dataset", "children": []}, {"dataset_id": 47235, "pid": "doi:10.34894/0CQ5SW", "type": "dataset", "children": []}, {"dataset_id": 141203, "pid": "doi:10.34894/LD03HF", "type": "dataset", "children": []}]}, {"dataverse_id": 17407, "title": "MERLN", "dataverse_alias": "MERLN", "type": "dataverse", "children": [{"dataset_id": 17433, "pid": "doi:10.34894/K4VATI", "type": "dataset", "children": []}, {"dataset_id": 17506, "pid": "doi:10.34894/8MONUL", "type": "dataset", "children": []}, {"dataset_id": 21008, "pid": "doi:10.34894/VVATM8", "type": "dataset", "children": []}, {"dataset_id": 25503, "pid": "doi:10.34894/TKYUBX", "type": "dataset", "children": []}, {"dataset_id": 25508, "pid": "doi:10.34894/ZF16CR", "type": "dataset", "children": []}, {"dataset_id": 28224, "pid": "doi:10.34894/TVNWAF", "type": "dataset", "children": []}, {"dataset_id": 31205, "pid": "doi:10.34894/0AC9LY", "type": "dataset", "children": []}, {"dataset_id": 38158, "pid": "doi:10.34894/UAL6GN", "type": "dataset", "children": []}, {"dataset_id": 39711, "pid": "doi:10.34894/A4NGLO", "type": "dataset", "children": []}, {"dataset_id": 40423, "pid": "doi:10.34894/B1KIXB", "type": "dataset", "children": []}, {"dataset_id": 46759, "pid": "doi:10.34894/JUS4U6", "type": "dataset", "children": []}, {"dataset_id": 94926, "pid": "doi:10.34894/XUOHLG", "type": "dataset", "children": []}, {"dataset_id": 111430, "pid": "doi:10.34894/F03MPH", "type": "dataset", "children": []}, {"dataset_id": 190986, "pid": "doi:10.34894/HBKOLJ", "type": "dataset", "children": []}, {"dataset_id": 191273, "pid": "doi:10.34894/X7ZSDZ", "type": "dataset", "children": []}, {"dataset_id": 223328, "pid": "doi:10.34894/GSOHSD", "type": "dataset", "children": []}, {"dataset_id": 235585, "pid": "doi:10.34894/0D0JXE", "type": "dataset", "children": []}, {"dataset_id": 269067, "pid": "doi:10.34894/VWMT6T", "type": "dataset", "children": []}, {"dataset_id": 296877, "pid": "doi:10.34894/KMRJPD", "type": "dataset", "children": []}, {"dataset_id": 297887, "pid": "doi:10.34894/N1EATZ", "type": "dataset", "children": []}, {"dataset_id": 297898, "pid": "doi:10.34894/S2QX6C", "type": "dataset", "children": []}, {"dataset_id": 308782, "pid": "doi:10.34894/LREYWG", "type": "dataset", "children": []}, {"dataset_id": 310204, "pid": "doi:10.34894/90WXR1", "type": "dataset", "children": []}, {"dataset_id": 310205, "pid": "doi:10.34894/YISKVU", "type": "dataset", "children": []}, {"dataset_id": 314397, "pid": "doi:10.34894/T4TPLJ", "type": "dataset", "children": []}, {"dataset_id": 314398, "pid": "doi:10.34894/YBQVZN", "type": "dataset", "children": []}]}, {"dataverse_id": 36570, "title": "Health, Ethics & Society (HES)", "dataverse_alias": "HES", "type": "dataverse", "children": [{"dataset_id": 36571, "pid": "doi:10.34894/UFM8MN", "type": "dataset", "children": []}, {"dataset_id": 46763, "pid": "doi:10.34894/EA03EC", "type": "dataset", "children": []}]}, {"dataverse_id": 94696, "title": "Health Services Research (HSR)", "dataverse_alias": "HSR", "type": "dataverse", "children": [{"dataverse_id": 100103, "title": "Improvise, adapt, overwork? Understanding and learning from hospitals' adaptations to COVID-19 and their effects on professional functioning and recovery.", "dataverse_alias": "Improvise-adapt-overwork", "type": "dataverse", "children": [{"dataverse_id": 100106, "title": "Improvise, adapt, overwork? (Qualitative)", "dataverse_alias": "Improvise-adapt-overwork-Qualitative", "type": "dataverse", "children": [{"dataset_id": 100107, "pid": "doi:10.34894/BPXVMZ", "type": "dataset", "children": []}, {"dataset_id": 100108, "pid": "doi:10.34894/FVFTBI", "type": "dataset", "children": []}, {"dataset_id": 100109, "pid": "doi:10.34894/NODI0Q", "type": "dataset", "children": []}]}, {"dataverse_id": 100114, "title": "Improvise, adapt, overwork? (Quantitative)", "dataverse_alias": "Improvise-adapt-overwork-Quantitative", "type": "dataverse", "children": [{"dataset_id": 100115, "pid": "doi:10.34894/TIDUND", "type": "dataset", "children": []}, {"dataset_id": 200189, "pid": "doi:10.34894/8QZFQQ", "type": "dataset", "children": []}, {"dataset_id": 222219, "pid": "doi:10.34894/CQK8VL", "type": "dataset", "children": []}]}, {"dataset_id": 320099, "pid": "doi:10.34894/SJBLDU", "type": "dataset", "children": []}]}, {"dataset_id": 94888, "pid": "doi:10.34894/2X2ZH5", "type": "dataset", "children": []}, {"dataset_id": 102455, "pid": "doi:10.34894/EENUHR", "type": "dataset", "children": []}, {"dataset_id": 195460, "pid": "doi:10.34894/PKRHGA", "type": "dataset", "children": []}, {"dataset_id": 268961, "pid": "doi:10.34894/OS1ZNY", "type": "dataset", "children": []}, {"dataset_id": 320746, "pid": "doi:10.34894/S7MN6E", "type": "dataset", "children": []}, {"dataset_id": 320968, "pid": "doi:10.34894/5VBOFU", "type": "dataset", "children": []}]}, {"dataverse_id": 141044, "title": "Social Medicine", "dataverse_alias": "socmed", "type": "dataverse", "children": [{"dataset_id": 141047, "pid": "doi:10.34894/ZJICTA", "type": "dataset", "children": []}]}, {"dataverse_id": 296909, "title": "Family Medicine", "dataverse_alias": "hag", "type": "dataverse", "children": [{"dataverse_id": 296917, "title": "Research Network Family Medicine (RNFM)", "dataverse_alias": "rnfm", "type": "dataverse", "children": [{"dataset_id": 308995, "pid": "doi:10.34894/TKIKNJ", "type": "dataset", "children": []}]}, {"dataverse_id": 300201, "title": "Healthy Primary School of the Future", "dataverse_alias": "gbt", "type": "dataverse", "children": [{"dataset_id": 300202, "pid": "doi:10.34894/JEIM3O", "type": "dataset", "children": []}, {"dataset_id": 300203, "pid": "doi:10.34894/ZLB24E", "type": "dataset", "children": []}]}, {"dataverse_id": 309083, "title": "PRO-COVID-19", "dataverse_alias": "pro-covid", "type": "dataverse", "children": [{"dataset_id": 309084, "pid": "doi:10.34894/HHYRIT", "type": "dataset", "children": []}, {"dataset_id": 309085, "pid": "doi:10.34894/ZGU9EO", "type": "dataset", "children": []}]}, {"dataset_id": 310336, "pid": "doi:10.34894/BFCHQJ", "type": "dataset", "children": []}]}, {"dataverse_id": 304084, "title": "M4I", "dataverse_alias": "MfourI", "type": "dataverse", "children": [{"dataset_id": 309868, "pid": "doi:10.34894/XKYD0Q", "type": "dataset", "children": []}]}, {"dataverse_id": 310299, "title": "Epidemiology", "dataverse_alias": "epid", "type": "dataverse", "children": [{"dataverse_id": 310300, "title": "Sport Genetics", "dataverse_alias": "sportgenetics", "type": "dataverse", "children": []}]}]}, {"dataverse_id": 719, "title": "Faculty of Arts and Social Sciences", "dataverse_alias": "FacultyofArtsandSocialSciences", "type": "dataverse", "children": [{"dataverse_id": 236, "title": "Arts, Media and Culture (AMC)", "dataverse_alias": "AMC", "type": "dataverse", "children": [{"dataset_id": 10835, "pid": "doi:10.34894/IMQPCO", "type": "dataset", "children": []}]}, {"dataverse_id": 237, "title": "Maastricht University Science, Technology and Society Studies (MUSTS)", "dataverse_alias": "MUSTS", "type": "dataverse", "children": [{"dataverse_id": 22416, "title": "'Making Clinical Sense' ", "dataverse_alias": "MCS", "type": "dataverse", "children": [{"dataset_id": 23443, "pid": "doi:10.34894/SJ4N6G", "type": "dataset", "children": []}]}, {"dataset_id": 8586, "pid": "doi:10.34894/DR3I2A", "type": "dataset", "children": []}, {"dataset_id": 36716, "pid": "doi:10.34894/LRBQF5", "type": "dataset", "children": []}, {"dataset_id": 94448, "pid": "doi:10.34894/ZG5GMB", "type": "dataset", "children": []}, {"dataset_id": 216339, "pid": "doi:10.34894/KTHLRV", "type": "dataset", "children": []}, {"dataset_id": 310206, "pid": "doi:10.34894/KPJKMV", "type": "dataset", "children": []}, {"dataset_id": 310350, "pid": "doi:10.34894/DT858J", "type": "dataset", "children": []}]}, {"dataverse_id": 238, "title": "Politics and Culture in Europe (PCE)", "dataverse_alias": "PCE", "type": "dataverse", "children": [{"dataverse_id": 116, "title": "Arjan Schakel", "dataverse_alias": "ArjanSchakel", "type": "dataverse", "children": [{"dataset_id": 661, "pid": "doi:10.34894/8MEEO2", "type": "dataset", "children": []}]}]}, {"dataverse_id": 239, "title": "Globalisation, Transnationalism and Development (GTD)", "dataverse_alias": "GTD", "type": "dataverse", "children": [{"dataverse_id": 23440, "title": "State-own-funds ", "dataverse_alias": "stateownfunds", "type": "dataverse", "children": [{"dataset_id": 23439, "pid": "doi:10.34894/BFZF0Y", "type": "dataset", "children": []}, {"dataset_id": 26841, "pid": "doi:10.34894/YYJYIC", "type": "dataset", "children": []}, {"dataset_id": 95815, "pid": "doi:10.34894/VUESC3", "type": "dataset", "children": []}]}, {"dataset_id": 303893, "pid": "doi:10.34894/1R5VTK", "type": "dataset", "children": []}]}, {"dataverse_id": 216376, "title": "MO-TRAYL", "dataverse_alias": "MO-TRAYL", "type": "dataverse", "children": [{"dataset_id": 216377, "pid": "doi:10.34894/QLTUZB", "type": "dataset", "children": []}]}, {"dataset_id": 310351, "pid": "doi:10.34894/XLFAQQ", "type": "dataset", "children": []}]}, {"dataverse_id": 733, "title": "Faculty of Law", "dataverse_alias": "law", "type": "dataverse", "children": [{"dataverse_id": 7482, "title": "Criminal Law and Criminology", "dataverse_alias": "CriminalLaw", "type": "dataverse", "children": [{"dataset_id": 7483, "pid": "doi:10.34894/NFECFD", "type": "dataset", "children": []}, {"dataset_id": 7491, "pid": "doi:10.34894/BCKFZ0", "type": "dataset", "children": []}, {"dataset_id": 18327, "pid": "doi:10.34894/NNRX8P", "type": "dataset", "children": []}, {"dataset_id": 93271, "pid": "doi:10.34894/SRSB8I", "type": "dataset", "children": []}]}, {"dataverse_id": 7485, "title": "International and European Law", "dataverse_alias": "international_and_european_law", "type": "dataverse", "children": [{"dataset_id": 18328, "pid": "doi:10.34894/UMF5VF", "type": "dataset", "children": []}, {"dataset_id": 39022, "pid": "doi:10.34894/HTDMW4", "type": "dataset", "children": []}, {"dataset_id": 212200, "pid": "doi:10.34894/SK0EUB", "type": "dataset", "children": []}]}, {"dataverse_id": 17169, "title": "Private Law", "dataverse_alias": "PrivateLaw", "type": "dataverse", "children": [{"dataset_id": 586, "pid": "doi:10.34894/6XTXVA", "type": "dataset", "children": []}, {"dataset_id": 9604, "pid": "doi:10.34894/Y2SHRZ", "type": "dataset", "children": []}, {"dataset_id": 17257, "pid": "doi:10.34894/NI0LHC", "type": "dataset", "children": []}, {"dataset_id": 26682, "pid": "doi:10.34894/8NA9UV", "type": "dataset", "children": []}, {"dataset_id": 141049, "pid": "doi:10.34894/SHPLTP", "type": "dataset", "children": []}, {"dataset_id": 191438, "pid": "doi:10.34894/4UTK2C", "type": "dataset", "children": []}]}, {"dataverse_id": 18457, "title": "Public Law", "dataverse_alias": "PublicLaw", "type": "dataverse", "children": []}, {"dataverse_id": 25264, "title": "Foundations and Methods of Law", "dataverse_alias": "FoundationsAndMethodsOfLaw", "type": "dataverse", "children": []}, {"dataverse_id": 25265, "title": "Tax Law", "dataverse_alias": "TaxLaw", "type": "dataverse", "children": [{"dataset_id": 105752, "pid": "doi:10.34894/U6PKC1", "type": "dataset", "children": []}]}, {"dataverse_id": 320117, "title": "Institute for Transnational Legal Research (METRO)", "dataverse_alias": "METRO", "type": "dataverse", "children": [{"dataset_id": 320118, "pid": "doi:10.34894/RHHGVV", "type": "dataset", "children": []}]}]}, {"dataverse_id": 734, "title": "Faculty of Science and Engineering", "dataverse_alias": "FSE", "type": "dataverse", "children": [{"dataverse_id": 185, "title": "International Centre for Integrated assessment and Sustainable development (ICIS)", "dataverse_alias": "ICIS", "type": "dataverse", "children": [{"dataset_id": 1297, "pid": "doi:10.34894/VJTCSN", "type": "dataset", "children": []}, {"dataset_id": 1298, "pid": "doi:10.34894/DGYP1H", "type": "dataset", "children": []}, {"dataset_id": 1299, "pid": "doi:10.34894/PPMCND", "type": "dataset", "children": []}, {"dataset_id": 1300, "pid": "doi:10.34894/BDH1BV", "type": "dataset", "children": []}]}, {"dataverse_id": 26686, "title": "Department of Advanced Computing Sciences (DACS)", "dataverse_alias": "DACS", "type": "dataverse", "children": [{"dataset_id": 201008, "pid": "doi:10.34894/7RAGMX", "type": "dataset", "children": []}, {"dataset_id": 285475, "pid": "doi:10.34894/Q80QUE", "type": "dataset", "children": []}, {"dataset_id": 308984, "pid": "doi:10.34894/NUWT5E", "type": "dataset", "children": []}, {"dataset_id": 314282, "pid": "doi:10.34894/BP8G8U", "type": "dataset", "children": []}, {"dataset_id": 322700, "pid": "doi:10.34894/8EVX4U", "type": "dataset", "children": []}]}, {"dataverse_id": 31179, "title": "Maastricht Centre for Systems Biology (MaCSBio)", "dataverse_alias": "MaCSBio", "type": "dataverse", "children": [{"dataset_id": 31180, "pid": "doi:10.34894/RNZI0A", "type": "dataset", "children": []}]}, {"dataverse_id": 106278, "title": "University College Maastricht (UCM)", "dataverse_alias": "UCM", "type": "dataverse", "children": [{"dataset_id": 268691, "pid": "doi:10.34894/3OYALS", "type": "dataset", "children": []}, {"dataset_id": 299054, "pid": "doi:10.34894/ZWKS0Y", "type": "dataset", "children": []}, {"dataset_id": 356808, "pid": "doi:10.34894/MQMPTT", "type": "dataset", "children": []}]}, {"dataverse_id": 309780, "title": "Aachen-Maastricht Institute for Biobased Materials (AMIBM)", "dataverse_alias": "AMIBM", "type": "dataverse", "children": []}, {"dataverse_id": 309781, "title": "University College Venlo", "dataverse_alias": "UCV", "type": "dataverse", "children": []}]}, {"dataverse_id": 10549, "title": "UNU-MERIT", "dataverse_alias": "UNU-MERIT", "type": "dataverse", "children": [{"dataverse_id": 17438, "title": "New mindsets to innovate activation", "dataverse_alias": "newmindsets", "type": "dataverse", "children": [{"dataset_id": 17485, "pid": "doi:10.34894/QDOY6E", "type": "dataset", "children": []}, {"dataset_id": 17488, "pid": "doi:10.34894/LDXCXG", "type": "dataset", "children": []}, {"dataset_id": 17646, "pid": "doi:10.34894/SVY4VJ", "type": "dataset", "children": []}]}, {"dataverse_id": 18228, "title": "All Technological Main Path Trajectories - PATSTAT", "dataverse_alias": "AllTechTrajectories", "type": "dataverse", "children": [{"dataset_id": 18229, "pid": "doi:10.34894/TR6B0W", "type": "dataset", "children": []}]}, {"dataverse_id": 20971, "title": "Far from random? The role of homophily in student supervision", "dataverse_alias": "Far_from_Random", "type": "dataverse", "children": [{"dataset_id": 20972, "pid": "doi:10.34894/R6F7VV", "type": "dataset", "children": []}, {"dataset_id": 20974, "pid": "doi:10.34894/UJ96QJ", "type": "dataset", "children": []}, {"dataset_id": 21005, "pid": "doi:10.34894/TDP8DH", "type": "dataset", "children": []}]}, {"dataverse_id": 21104, "title": "Cycles, Economic Structures and External Constraints : A Structuralists Study on the Causes of Economic Volatility in Latin America", "dataverse_alias": "Cycles_Economic_Structures_and_External_Constraints", "type": "dataverse", "children": [{"dataset_id": 21106, "pid": "doi:10.34894/LQTBTX", "type": "dataset", "children": []}, {"dataset_id": 21108, "pid": "doi:10.34894/SYV70C", "type": "dataset", "children": []}]}, {"dataverse_id": 23449, "title": "Essays on Rural Household Decision-Making under Climate Risk", "dataverse_alias": "Rural_Household_Decision-Making_under_Climate_Risk", "type": "dataverse", "children": [{"dataset_id": 23450, "pid": "doi:10.34894/MT9BPY", "type": "dataset", "children": []}, {"dataset_id": 23452, "pid": "doi:10.34894/PF4NF4", "type": "dataset", "children": []}, {"dataset_id": 23454, "pid": "doi:10.34894/JEHGQB", "type": "dataset", "children": []}]}, {"dataverse_id": 23464, "title": "Diaspora Mobilisation in a Conflict Setting: The Emergence and Trajectories of Syrian Diaspora Mobilisation in Germany", "dataverse_alias": "Diaspora_Mobilisation_in_a_Conflict_Setting", "type": "dataverse", "children": [{"dataset_id": 23465, "pid": "doi:10.34894/EZT9XR", "type": "dataset", "children": []}, {"dataset_id": 23466, "pid": "doi:10.34894/XU1H1M", "type": "dataset", "children": []}]}, {"dataverse_id": 24583, "title": "Student Migrant, Refugee or Both? Exploring refugee agency and mobility through tertiary education in Kenya, South Africa, and Uganda", "dataverse_alias": "Student_Migrant_Refugee_or_Both", "type": "dataverse", "children": [{"dataset_id": 24584, "pid": "doi:10.34894/Z9CRYB", "type": "dataset", "children": []}]}, {"dataverse_id": 27291, "title": "Playing the Game of Transparency and Accountability in Kyrgyzstan's Resource Governance", "dataverse_alias": "Playing_the_Game", "type": "dataverse", "children": [{"dataset_id": 27292, "pid": "doi:10.34894/RKBABX", "type": "dataset", "children": []}, {"dataset_id": 27294, "pid": "doi:10.34894/VOOLDT", "type": "dataset", "children": []}]}, {"dataverse_id": 36573, "title": "The transition from primary to secondary education: a study of the voices of children and teachers in the  Netherlands", "dataverse_alias": "The_transition_from_primary_to_secondary_education", "type": "dataverse", "children": [{"dataset_id": 36580, "pid": "doi:10.34894/FUTZPJ", "type": "dataset", "children": []}, {"dataset_id": 36582, "pid": "doi:10.34894/RVQZ4F", "type": "dataset", "children": []}, {"dataset_id": 36585, "pid": "doi:10.34894/MCVJ7D", "type": "dataset", "children": []}, {"dataset_id": 36588, "pid": "doi:10.34894/OYVNSJ", "type": "dataset", "children": []}]}, {"dataverse_id": 36594, "title": "Structural change in developing countries: patterns, causes and consequences", "dataverse_alias": "Structural_change_in_developing_countries", "type": "dataverse", "children": [{"dataset_id": 36604, "pid": "doi:10.34894/UWEKIZ", "type": "dataset", "children": []}, {"dataset_id": 36610, "pid": "doi:10.34894/8UZTDX", "type": "dataset", "children": []}, {"dataset_id": 36663, "pid": "doi:10.34894/0TIPON", "type": "dataset", "children": []}, {"dataset_id": 36676, "pid": "doi:10.34894/HHHGWJ", "type": "dataset", "children": []}]}, {"dataverse_id": 36732, "title": "International Organizations and Global Migration Governance", "dataverse_alias": "international_organizations_and_global_migration_governance", "type": "dataverse", "children": [{"dataset_id": 36733, "pid": "doi:10.34894/EGV3MO", "type": "dataset", "children": []}, {"dataset_id": 36735, "pid": "doi:10.34894/OESMRY", "type": "dataset", "children": []}, {"dataset_id": 36737, "pid": "doi:10.34894/FZX9MH", "type": "dataset", "children": []}, {"dataset_id": 36739, "pid": "doi:10.34894/6X7LLY", "type": "dataset", "children": []}, {"dataset_id": 36795, "pid": "doi:10.34894/NUH0NN", "type": "dataset", "children": []}, {"dataset_id": 36797, "pid": "doi:10.34894/FGXRQI", "type": "dataset", "children": []}, {"dataset_id": 36799, "pid": "doi:10.34894/GLOTYF", "type": "dataset", "children": []}, {"dataset_id": 36801, "pid": "doi:10.34894/1MYHBY", "type": "dataset", "children": []}]}, {"dataverse_id": 38830, "title": "Emergent structures in faculty hiring networks, and the effects of mobility on academic performance.", "dataverse_alias": "Emergent_structures_in_faculty_hiring_networks", "type": "dataverse", "children": [{"dataset_id": 38831, "pid": "doi:10.34894/CESCTL", "type": "dataset", "children": []}, {"dataset_id": 38833, "pid": "doi:10.34894/JL4XAS", "type": "dataset", "children": []}]}, {"dataverse_id": 38835, "title": "Ph.D. research output in STEM: the role of gender and race in supervision", "dataverse_alias": "PhD_research_output_in_STEM", "type": "dataverse", "children": [{"dataset_id": 38841, "pid": "doi:10.34894/RDUUX7", "type": "dataset", "children": []}, {"dataset_id": 38843, "pid": "doi:10.34894/MAMKEM", "type": "dataset", "children": []}]}, {"dataverse_id": 38860, "title": "Learning, Capabilities and Governance in Global Value Chains", "dataverse_alias": "Learning_Capabilities_and_Governance_in_Global_Value_Chains", "type": "dataverse", "children": [{"dataset_id": 38863, "pid": "doi:10.34894/BAH5AO", "type": "dataset", "children": []}, {"dataset_id": 38867, "pid": "doi:10.34894/L8DZJR", "type": "dataset", "children": []}]}, {"dataverse_id": 40274, "title": "Governance of international adaptation finance for local climate change adaptation: An analysis of Adaptation Fund projects.", "dataverse_alias": "Governance_of_international_adaptation_finance", "type": "dataverse", "children": [{"dataset_id": 40275, "pid": "doi:10.34894/EPPKTM", "type": "dataset", "children": []}, {"dataset_id": 40277, "pid": "doi:10.34894/TPL4OI", "type": "dataset", "children": []}, {"dataset_id": 40279, "pid": "doi:10.34894/0KSWWP", "type": "dataset", "children": []}]}, {"dataverse_id": 94556, "title": "Essays on Informal versus Formal Economy Choices", "dataverse_alias": "Essays_on_Informal_versus_Formal_Economy_Choices", "type": "dataverse", "children": [{"dataset_id": 94557, "pid": "doi:10.34894/OHWFJU", "type": "dataset", "children": []}]}, {"dataverse_id": 94697, "title": "A quantitative approach to the right to education: Concept, measurement, and effects", "dataverse_alias": "A_quantitative_approach_to_the_right_to_education", "type": "dataverse", "children": [{"dataset_id": 94698, "pid": "doi:10.34894/JRITXY", "type": "dataset", "children": []}, {"dataset_id": 94706, "pid": "doi:10.34894/APGNID", "type": "dataset", "children": []}, {"dataset_id": 94708, "pid": "doi:10.34894/MO0FZB", "type": "dataset", "children": []}, {"dataset_id": 94801, "pid": "doi:10.34894/45CVDB", "type": "dataset", "children": []}]}, {"dataverse_id": 95940, "title": "Unveiling the Determinants of Scientific Productivity in Middle Income Countries: An Economics of Science Perspective", "dataverse_alias": "Unveiling_the_Determinants_of_Scientific_Productivity", "type": "dataverse", "children": [{"dataset_id": 95941, "pid": "doi:10.34894/KR3FCW", "type": "dataset", "children": []}, {"dataset_id": 95954, "pid": "doi:10.34894/LYJ9IY", "type": "dataset", "children": []}, {"dataset_id": 95959, "pid": "doi:10.34894/P6TU6G", "type": "dataset", "children": []}, {"dataset_id": 95964, "pid": "doi:10.34894/5XDWLH", "type": "dataset", "children": []}]}, {"dataverse_id": 105762, "title": "Powering Structural Transformation and Economic Development in Africa", "dataverse_alias": "powering_structural_transformation", "type": "dataverse", "children": [{"dataset_id": 105763, "pid": "doi:10.34894/N91KBQ", "type": "dataset", "children": []}, {"dataset_id": 105772, "pid": "doi:10.34894/1BHZIM", "type": "dataset", "children": []}, {"dataset_id": 105825, "pid": "doi:10.34894/KKOJWH", "type": "dataset", "children": []}, {"dataset_id": 105850, "pid": "doi:10.34894/TA600S", "type": "dataset", "children": []}]}, {"dataverse_id": 106657, "title": "A Multidimensional Perspective on Education in Developing Countries", "dataverse_alias": "Multidimensional_Perspective_on_Education", "type": "dataverse", "children": [{"dataset_id": 106658, "pid": "doi:10.34894/YIIZR4", "type": "dataset", "children": []}, {"dataset_id": 106671, "pid": "doi:10.34894/I9IUTO", "type": "dataset", "children": []}, {"dataset_id": 106674, "pid": "doi:10.34894/XAASJL", "type": "dataset", "children": []}]}, {"dataverse_id": 139763, "title": "Markets and Human Behavior: Evidence from Artefactual Field Experiments", "dataverse_alias": "markets_and_human_behavior", "type": "dataverse", "children": [{"dataset_id": 139765, "pid": "doi:10.34894/S7TUCD", "type": "dataset", "children": []}, {"dataset_id": 139771, "pid": "doi:10.34894/6KLOZN", "type": "dataset", "children": []}, {"dataset_id": 139777, "pid": "doi:10.34894/KLFDMV", "type": "dataset", "children": []}]}, {"dataverse_id": 140845, "title": "Monitoring the open access policy of Horizon 2020", "dataverse_alias": "Monitoring_the_open_access_policy_of_Horizon_2020", "type": "dataverse", "children": [{"dataset_id": 140846, "pid": "doi:10.34894/XBZYRL", "type": "dataset", "children": []}, {"dataset_id": 140848, "pid": "doi:10.34894/DWPI4G", "type": "dataset", "children": []}, {"dataset_id": 140850, "pid": "doi:10.34894/X0DFZ2", "type": "dataset", "children": []}]}, {"dataverse_id": 191439, "title": "BIGPROD Data & Information", "dataverse_alias": "BIGPROD_Data_Sample", "type": "dataverse", "children": [{"dataset_id": 191440, "pid": "doi:10.34894/CI5XRR", "type": "dataset", "children": []}, {"dataset_id": 192681, "pid": "doi:10.34894/2ST1AN", "type": "dataset", "children": []}, {"dataset_id": 199553, "pid": "doi:10.34894/W3W2JQ", "type": "dataset", "children": []}, {"dataset_id": 204440, "pid": "doi:10.34894/OJMSMZ", "type": "dataset", "children": []}, {"dataset_id": 235401, "pid": "doi:10.34894/BS9XVR", "type": "dataset", "children": []}, {"dataset_id": 269072, "pid": "doi:10.34894/Y6WS6Y", "type": "dataset", "children": []}, {"dataset_id": 269077, "pid": "doi:10.34894/R99TRK", "type": "dataset", "children": []}, {"dataset_id": 269098, "pid": "doi:10.34894/V7EIW5", "type": "dataset", "children": []}, {"dataset_id": 269139, "pid": "doi:10.34894/9DSWVT", "type": "dataset", "children": []}, {"dataset_id": 291129, "pid": "doi:10.34894/8GACJV", "type": "dataset", "children": []}]}, {"dataverse_id": 192668, "title": "The Negotiations of Zambia\u2019s Welfare Regime : The Transformative Potential of Social Cash Transfers", "dataverse_alias": "Negotiations_of_Zambias_Welfare_Regime", "type": "dataverse", "children": [{"dataset_id": 192669, "pid": "doi:10.34894/D8DRJP", "type": "dataset", "children": []}, {"dataset_id": 192671, "pid": "doi:10.34894/98LNNJ", "type": "dataset", "children": []}]}, {"dataverse_id": 195471, "title": "Public Sector Innovation in the United Arab Emirates: How innovation occurs and the outcomes it delivers ", "dataverse_alias": "Public_Sector_Innovation_in_the_United_Arab_Emirates", "type": "dataverse", "children": [{"dataset_id": 195472, "pid": "doi:10.34894/V2N1U2", "type": "dataset", "children": []}, {"dataset_id": 195474, "pid": "doi:10.34894/9FDT4K", "type": "dataset", "children": []}]}, {"dataverse_id": 196623, "title": "Towards e-compliance: Exploring the role of compliance and e-governance initiatives in the case of Bhutan", "dataverse_alias": "towards_e-compliance", "type": "dataverse", "children": [{"dataset_id": 196624, "pid": "doi:10.34894/6K5OJE", "type": "dataset", "children": []}, {"dataset_id": 196626, "pid": "doi:10.34894/EOYVPO", "type": "dataset", "children": []}, {"dataset_id": 196628, "pid": "doi:10.34894/HVOB8K", "type": "dataset", "children": []}, {"dataset_id": 196630, "pid": "doi:10.34894/WFWNLO", "type": "dataset", "children": []}]}, {"dataverse_id": 199812, "title": "Labour\u2010augmenting technical change data for alternative elasticities of substitution, growth, slowdown, and distribution dynamics", "dataverse_alias": "Labour-augmenting_technical_change_data", "type": "dataverse", "children": [{"dataset_id": 199813, "pid": "doi:10.34894/VGA1NW", "type": "dataset", "children": []}]}, {"dataverse_id": 199815, "title": "Global dynamics of Gini coefficients of education for 146 countries updated to 1950\u20102015", "dataverse_alias": "Global_dynamics_of_Gini_coefficients_of_education", "type": "dataverse", "children": [{"dataset_id": 199816, "pid": "doi:10.34894/I1MFXW", "type": "dataset", "children": []}]}, {"dataverse_id": 200191, "title": "Effects of HIV on Children and Youth's Educational Attainment", "dataverse_alias": "Effects_of_HIV_on_Children_and_Youths_Educational_Attainment", "type": "dataverse", "children": [{"dataset_id": 200192, "pid": "doi:10.34894/SVBK00", "type": "dataset", "children": []}, {"dataset_id": 200195, "pid": "doi:10.34894/FIRTQS", "type": "dataset", "children": []}, {"dataset_id": 200198, "pid": "doi:10.34894/2UOFWA", "type": "dataset", "children": []}]}, {"dataverse_id": 200309, "title": "Immigrant Welfare Dynamics in the Netherlands", "dataverse_alias": "Immigrant_welfare_dynamics_in_the_Netherlands", "type": "dataverse", "children": [{"dataset_id": 200310, "pid": "doi:10.34894/96WVXA", "type": "dataset", "children": []}]}, {"dataverse_id": 269183, "title": "Limiting Media Freedom in Democratic States: How Governments Use Instruments to Curtail News Media Freedom", "dataverse_alias": "Limiting_Media_Freedom_in_Democratic_States", "type": "dataverse", "children": [{"dataset_id": 269184, "pid": "doi:10.34894/WIJM9C", "type": "dataset", "children": []}, {"dataset_id": 269187, "pid": "doi:10.34894/HBJXWO", "type": "dataset", "children": []}]}, {"dataverse_id": 299059, "title": "Beyond the Right to Work: Labour Market Engagement of Protracted Refugees Through a Social Exclusion Lens", "dataverse_alias": "Beyond_the_Right_to_Work", "type": "dataverse", "children": [{"dataset_id": 299060, "pid": "doi:10.34894/FHHSYH", "type": "dataset", "children": []}, {"dataset_id": 299072, "pid": "doi:10.34894/Q4MEQV", "type": "dataset", "children": []}, {"dataset_id": 299085, "pid": "doi:10.34894/M6TCO5", "type": "dataset", "children": []}]}, {"dataverse_id": 299090, "title": "Essays on Human and Social Capital Formation", "dataverse_alias": "Essays_on_Human_and_Social_Capital_Formation", "type": "dataverse", "children": [{"dataset_id": 299091, "pid": "doi:10.34894/MNJN3O", "type": "dataset", "children": []}, {"dataset_id": 299097, "pid": "doi:10.34894/LORELL", "type": "dataset", "children": []}]}, {"dataverse_id": 299838, "title": "The Changing Role of Communication Technology in Reproductive Health: Essays from Sub-Saharan Africa", "dataverse_alias": "Communication_Technology_in_Reproductive_Health", "type": "dataverse", "children": [{"dataset_id": 299839, "pid": "doi:10.34894/XR7GSL", "type": "dataset", "children": []}, {"dataset_id": 299842, "pid": "doi:10.34894/BY2TKN", "type": "dataset", "children": []}, {"dataset_id": 299845, "pid": "doi:10.34894/10OZBQ", "type": "dataset", "children": []}, {"dataset_id": 299849, "pid": "doi:10.34894/EWXXNM", "type": "dataset", "children": []}]}, {"dataverse_id": 299852, "title": "Inter-Municipal Cooperation and Environmental Outcomes: Impact, drivers, and incentives", "dataverse_alias": "Inter-Municipal_Cooperation_and_Environmental_Outcomes", "type": "dataverse", "children": [{"dataset_id": 299853, "pid": "doi:10.34894/QLK2T2", "type": "dataset", "children": []}, {"dataset_id": 299861, "pid": "doi:10.34894/L122R5", "type": "dataset", "children": []}]}, {"dataverse_id": 299870, "title": "LED there be light : The evolution in LED technology and dynamics of entry into the LED lighting market", "dataverse_alias": "LED_there_be_light", "type": "dataverse", "children": [{"dataset_id": 299888, "pid": "doi:10.34894/C2KBVW", "type": "dataset", "children": []}, {"dataset_id": 299893, "pid": "doi:10.34894/GLYLEG", "type": "dataset", "children": []}, {"dataset_id": 299898, "pid": "doi:10.34894/EUUE7L", "type": "dataset", "children": []}, {"dataset_id": 310008, "pid": "doi:10.34894/WTGHO5", "type": "dataset", "children": []}]}, {"dataverse_id": 309754, "title": "The Economic Outcomes of Financial Innovation and Digital Infrastructure in Sub-Saharan Africa", "dataverse_alias": "economic_outcomes_of_financial_innovation_and_digital_infra", "type": "dataverse", "children": [{"dataset_id": 309755, "pid": "doi:10.34894/VJVUVE", "type": "dataset", "children": []}, {"dataset_id": 309759, "pid": "doi:10.34894/L9NIJ2", "type": "dataset", "children": []}, {"dataset_id": 309765, "pid": "doi:10.34894/JOLEGS", "type": "dataset", "children": []}, {"dataset_id": 309775, "pid": "doi:10.34894/EAJYND", "type": "dataset", "children": []}]}, {"dataverse_id": 318688, "title": "Technical change, competitiveness, and employment: A sustainable perspective", "dataverse_alias": "Technical_change_competitiveness_and_employment", "type": "dataverse", "children": [{"dataset_id": 318690, "pid": "doi:10.34894/UI4NOI", "type": "dataset", "children": []}, {"dataset_id": 318697, "pid": "doi:10.34894/MGKVWO", "type": "dataset", "children": []}, {"dataset_id": 318703, "pid": "doi:10.34894/YEANTW", "type": "dataset", "children": []}, {"dataset_id": 318803, "pid": "doi:10.34894/RHVAMO", "type": "dataset", "children": []}]}, {"dataverse_id": 320752, "title": "Strategic mechanisms for stimulating academia-industry interactions in Rwanda", "dataverse_alias": "stimulating_academia-industry_interactions_in_Rwanda", "type": "dataverse", "children": [{"dataset_id": 320753, "pid": "doi:10.34894/EL6RAF", "type": "dataset", "children": []}, {"dataset_id": 320755, "pid": "doi:10.34894/KIPV7X", "type": "dataset", "children": []}, {"dataset_id": 320758, "pid": "doi:10.34894/U51JNE", "type": "dataset", "children": []}, {"dataset_id": 320762, "pid": "doi:10.34894/OLWGXF", "type": "dataset", "children": []}]}, {"dataverse_id": 351911, "title": "H2020 - Excellent Science Study: Annex 3 Additional Data", "dataverse_alias": "ESS_Annex_3_Additional_Data", "type": "dataverse", "children": [{"dataset_id": 351912, "pid": "doi:10.34894/SXKFGB", "type": "dataset", "children": []}, {"dataset_id": 351914, "pid": "doi:10.34894/301S7V", "type": "dataset", "children": []}, {"dataset_id": 352326, "pid": "doi:10.34894/YLUPYA", "type": "dataset", "children": []}, {"dataset_id": 353351, "pid": "doi:10.34894/DAUMLN", "type": "dataset", "children": []}]}, {"dataverse_id": 352618, "title": "Science Parks, Firm Performance and Knowledge Spillovers: Evidence from China", "dataverse_alias": "science_parks_firm_performance_and_knowledge_spillovers", "type": "dataverse", "children": [{"dataset_id": 352619, "pid": "doi:10.34894/QEY18X", "type": "dataset", "children": []}, {"dataset_id": 352623, "pid": "doi:10.34894/C5I9PM", "type": "dataset", "children": []}, {"dataset_id": 352628, "pid": "doi:10.34894/DVHWUP", "type": "dataset", "children": []}]}, {"dataverse_id": 356964, "title": "ICT Capabilities, Innovation and Economic Performance in Africa: The Role of Framework Conditions, Entrepreneurial Activity and Firm Learning", "dataverse_alias": "ICT_Capabilities_Innovation_and_Economic_Performance", "type": "dataverse", "children": [{"dataset_id": 356965, "pid": "doi:10.34894/PEPP01", "type": "dataset", "children": []}, {"dataset_id": 356968, "pid": "doi:10.34894/BTVZSL", "type": "dataset", "children": []}, {"dataset_id": 356972, "pid": "doi:10.34894/ECNZZG", "type": "dataset", "children": []}]}, {"dataset_id": 10550, "pid": "doi:10.34894/XBYD80", "type": "dataset", "children": []}]}, {"dataverse_id": 16336, "title": "DataHub", "dataverse_alias": "DataHub", "type": "dataverse", "children": [{"dataset_id": 141198, "pid": "doi:10.34894/PJTTMJ", "type": "dataset", "children": []}, {"dataset_id": 141199, "pid": "doi:10.34894/TEYEDK", "type": "dataset", "children": []}, {"dataset_id": 320425, "pid": "doi:10.34894/TAHYTW", "type": "dataset", "children": []}, {"dataset_id": 353320, "pid": "doi:10.34894/IYTRNF", "type": "dataset", "children": []}, {"dataset_id": 353373, "pid": "doi:10.34894/DIDYBY", "type": "dataset", "children": []}, {"dataset_id": 353558, "pid": "doi:10.34894/9LXD6X", "type": "dataset", "children": []}, {"dataset_id": 354170, "pid": "doi:10.34894/0KHD2B", "type": "dataset", "children": []}]}, {"dataverse_id": 17419, "title": "Maastricht UMC+", "dataverse_alias": "MUMC", "type": "dataverse", "children": [{"dataset_id": 18425, "pid": "doi:10.34894/AAOCQL", "type": "dataset", "children": []}, {"dataset_id": 28182, "pid": "doi:10.34894/OZVNMG", "type": "dataset", "children": []}, {"dataset_id": 39347, "pid": "doi:10.34894/SGKIMW", "type": "dataset", "children": []}, {"dataset_id": 221763, "pid": "doi:10.34894/VKERXP", "type": "dataset", "children": []}]}]